clockblocks/__init__.py
clockblocks/clock.py
clockblocks/debug.py
clockblocks/settings.py
clockblocks/tempo_envelope.py
clockblocks/utilities.py
clockblocks-0.6.7.dist-info/LICENSE
clockblocks-0.6.7.dist-info/METADATA
clockblocks-0.6.7.dist-info/WHEEL
clockblocks-0.6.7.dist-info/top_level.txt
clockblocks-0.6.7.dist-info/RECORD
