Metadata-Version: 2.1
Name: clockblocks
Version: 0.6.7
Summary: A python library for controlling the flow of musical time.
Home-page: https://git.sr.ht/~marcevanstein/clockblocks
Author: Marc Evanstein
Author-email: marc@marcevanstein.com
License: UNKNOWN
Platform: UNKNOWN
Classifier: Programming Language :: Python :: 3
Classifier: License :: OSI Approved :: GNU General Public License v3 (GPLv3)
Classifier: Operating System :: OS Independent
Requires-Dist: expenvelope (>=0.7.0)
